{"index.md":"99f75ef1","full-stack_java_oop_abstract.md":"e09b9b8f","about_index.md":"9de224a9","question-by-day_2024_11.md":"1caaafdd","full-stack_index.md":"13cfc6ef","question-by-day_2024_7.md":"724215dd","question-by-day_2024_1.md":"39b950b3","question-by-day_2023_9.md":"bf051c4d","technology_web_wordpress-by-docker-compose.md":"5cb08458","technology_web_acme-sh.md":"e23124b1","question-by-day_2024_4.md":"3016d73a","question-by-day_2023_12.md":"825292a6","question-by-day_2024_10.md":"218f1411","full-stack_java_characteristic_functional.md":"0304ab3a","question-by-day_2024_2.md":"c065222b","question-by-day_2024_5.md":"2af2db16","friend-link-list_index.md":"fa30fa61","question-by-day_index.md":"14cc0e61","question-by-day_2024_index.md":"517dba5e","technology_web_linux-lamp_second.md":"e5de8100","question-by-day_2023_10.md":"f7f29101","question-by-day_2023_index.md":"43d76fec","full-stack_java_index.md":"8f83776c","question-by-day_2023_11.md":"1e963e95","question-by-day_2024_9.md":"e076200b","question-by-day_2024_6.md":"043249d2","question-by-day_2024_12.md":"ffc094c9","question-by-day_2024_3.md":"807adf0a","share_index.md":"2d7bb6ee","technology_web_linux-lamp_first.md":"efea48b5","technology_web_linux-lamp_index.md":"491ab1a0","technology_web_linux-lamp_third.md":"e808491c","technology_web_index.md":"695d6493","question-by-day_2024_8.md":"5bba414d"}
